ass_tag_parser/__init__.py
ass_tag_parser/ass_composer.py
ass_tag_parser/ass_parser.py
ass_tag_parser/ass_struct.py
ass_tag_parser/common.py
ass_tag_parser/draw_composer.py
ass_tag_parser/draw_parser.py
ass_tag_parser/draw_struct.py
ass_tag_parser/errors.py
ass_tag_parser/io.py
ass_tag_parser/py.typed
ass_tag_parser/tests/__init__.py
ass_tag_parser/tests/conftest.py
ass_tag_parser/tests/test_ass_composing.py
ass_tag_parser/tests/test_ass_parsing.py
ass_tag_parser/tests/test_documentation.py
ass_tag_parser/tests/test_draw_composing.py
ass_tag_parser/tests/test_draw_parsing.py
ass_tag_parser/tests/test_module_exports.py
ass_tag_parser-2.4.1.dist-info/LICENSE.md
ass_tag_parser-2.4.1.dist-info/WHEEL
ass_tag_parser-2.4.1.dist-info/METADATA
ass_tag_parser-2.4.1.dist-info/RECORD
