Metadata-Version: 2.1
Name: ass-tag-parser
Version: 2.4.1
Summary: Parse ASS subtitle format tags markup.
Home-page: https://github.com/bubblesub/ass_tag_parser
License: MIT
Author: Marcin Kurczewski
Author-email: dash@wind.garden
Requires-Python: >=3.9
Classifier: Development Status :: 4 - Beta
Classifier: Environment :: Other Environment
Classifier: Intended Audience :: Developers
Classifier: License :: OSI Approved :: MIT License
Classifier: Natural Language :: English
Classifier: Operating System :: OS Independent
Classifier: Programming Language :: Python :: 3
Classifier: Programming Language :: Python :: 3.10
Classifier: Programming Language :: Python :: 3.9
Classifier: Topic :: Software Development :: Libraries :: Python Modules
Classifier: Topic :: Text Processing :: Markup
Project-URL: Repository, https://github.com/bubblesub/ass_tag_parser
